fedcast/__init__.py
fedcast/cast_models/__init__.py
fedcast/cast_models/linear.py
fedcast/cast_models/mlp.py
fedcast/datasets/__init__.py
fedcast/datasets/dataset_ecg.py
fedcast/datasets/dataset_eld.py
fedcast/datasets/dataset_intel_iot.py
fedcast/datasets/dataset_network_traffic.py
fedcast/datasets/dataset_sinus.py
fedcast/datasets/dataset_stocks.py
fedcast/datasets/dataset_weather.py
fedcast/experiments/__init__.py
fedcast/experiments/basic_fedavg.py
fedcast/experiments/basic_fedtrend.py
fedcast/experiments/grid_all.py
fedcast/federated_learning_strategies/__init__.py
fedcast/federated_learning_strategies/base.py
fedcast/federated_learning_strategies/fed_trend.py
fedcast/federated_learning_strategies/feddyn.py
fedcast/federated_learning_strategies/fedlama.py
fedcast/federated_learning_strategies/fednova.py
fedcast/federated_learning_strategies/fedopt.py
fedcast/federated_learning_strategies/fedprox.py
fedcast/federated_learning_strategies/partial_sampling.py
fedcast/federated_learning_strategies/scaffold.py
fedcast/telemetry/__init__.py
fedcast/telemetry/mlflow_logger.py
fedcast-0.1.1b1.dist-info/LICENSE
fedcast-0.1.1b1.dist-info/METADATA
fedcast-0.1.1b1.dist-info/WHEEL
fedcast-0.1.1b1.dist-info/RECORD
