Metadata-Version: 2.3
Name: fedcast
Version: 0.1.1b1
Summary: A modular framework for time series forecasting using federated learning, built on top of the Flower framework
License: Apache-2.0
Keywords: federated-learning,time-series,forecasting,machine-learning,flower,privacy
Author: FedCast Team
Author-email: nk@data-convolution.de
Requires-Python: >=3.9.2,<=3.13.2
Classifier: Development Status :: 4 - Beta
Classifier: Intended Audience :: Developers
Classifier: Intended Audience :: Science/Research
Classifier: License :: OSI Approved :: Apache Software License
Classifier: Operating System :: OS Independent
Classifier: Programming Language :: Python :: 3
Classifier: Programming Language :: Python :: 3.10
Classifier: Programming Language :: Python :: 3.11
Classifier: Programming Language :: Python :: 3.12
Classifier: Programming Language :: Python :: 3.13
Classifier: Programming Language :: Python :: 3.9
Classifier: Topic :: Scientific/Engineering :: Artificial Intelligence
Classifier: Topic :: Software Development :: Libraries :: Python Modules
Requires-Dist: datasets (>=3.1.0,<4.0.0)
Requires-Dist: flwr-datasets (>=0.5.0,<0.6.0)
Requires-Dist: flwr[simulation] (>=1.18.0,<2.0.0)
Requires-Dist: mlflow (>=2.15,<3.0)
Requires-Dist: pandas (>=2.2.3,<3.0.0)
Requires-Dist: tensorflow (>=2.15,<3.0)
Requires-Dist: tensorflow-metal (>=1.1.0,<2.0.0) ; sys_platform == "darwin" and platform_machine == "arm64"
Requires-Dist: torch (>=2.3,<3.0)
Requires-Dist: torchvision
Requires-Dist: wfdb (>=4.1.2,<5.0.0)
Requires-Dist: yfinance (>=0.2.40,<0.3.0)
Project-URL: Documentation, https://github.com/NKDataConv/FedCast#readme
Project-URL: Homepage, https://github.com/NKDataConv/FedCast
Project-URL: Repository, https://github.com/NKDataConv/FedCast
